asynclogger/__init__.py
asynclogger-0.1.0.dist-info/METADATA
asynclogger-0.1.0.dist-info/WHEEL
asynclogger-0.1.0.dist-info/top_level.txt
asynclogger-0.1.0.dist-info/RECORD
