Metadata-Version: 2.2
Name: asynclogger
Version: 0.1.0
Summary: A lightweight and efficient asynchronous logging package for Python
Home-page: https://github.com/ixlammm/asynclogger
Author: Islam Tazerout
Author-email: islamtazerout3@gmail.com
Classifier: Programming Language :: Python :: 3
Classifier: License :: OSI Approved :: MIT License
Classifier: Operating System :: OS Independent
Requires-Python: >=3.6
Requires-Dist: aiofile
Requires-Dist: colorist
Dynamic: author
Dynamic: author-email
Dynamic: classifier
Dynamic: description
Dynamic: description-content-type
Dynamic: home-page
Dynamic: requires-dist
Dynamic: requires-python
Dynamic: summary
